Barberchop/ExtractionService.py
Barberchop/__init__.py
Barberchop-1.0.1.dist-info/LICENSE
Barberchop-1.0.1.dist-info/METADATA
Barberchop-1.0.1.dist-info/WHEEL
Barberchop-1.0.1.dist-info/top_level.txt
Barberchop-1.0.1.dist-info/RECORD
