Metadata-Version: 2.1
Name: Barberchop
Version: 1.0.1
Summary: Segments, classifies and extracts barcode images from larger images containing one or more barcodes.
Home-page: https://github.com/sparkfish/barberchop
Author: Sparkfish LLC
Author-email: packages@sparkfish.com
License: UNKNOWN
Project-URL: Bug Tracker, https://github.com/sparkfish/barberchop/issues
Platform: UNKNOWN
Classifier: Programming Language :: Python :: 3
Classifier: License :: OSI Approved :: MIT License
Classifier: Operating System :: OS Independent
Requires-Python: >=3.7
License-File: LICENSE
Requires-Dist: yolov5 (==4.0.14)
